adb_pywrapper/__init__.py
adb_pywrapper/adb_device.py
adb_pywrapper/adb_result.py
adb_pywrapper/adb_screen_recorder.py
adb_pywrapper/pull_result.py
adb_pywrapper-1.3.0.dist-info/licenses/LICENSE.txt
test/__init__.py
test/test_adb_device.py
test/test_adb_pywrapper.py
adb_pywrapper-1.3.0.dist-info/METADATA
adb_pywrapper-1.3.0.dist-info/WHEEL
adb_pywrapper-1.3.0.dist-info/top_level.txt
adb_pywrapper-1.3.0.dist-info/RECORD
