Metadata-Version: 2.4
Name: adb_pywrapper
Version: 1.3.0
Summary: adb_pywrapper facilitates seamless interaction with Android devices using the Android Debug Bridge (ADB) directly within Python scripts.
Home-page: https://github.com/NetherlandsForensicInstitute/adb-pywrapper
Author: Netherlands Forensic Institute
Author-email: netherlandsforensicinstitute@users.noreply.github.com
License: EUPL-1.2
License-File: LICENSE.txt
Dynamic: author
Dynamic: author-email
Dynamic: description
Dynamic: description-content-type
Dynamic: home-page
Dynamic: license
Dynamic: license-file
Dynamic: summary
